{
  "main": {
    "id": "6ba8cf78df0cbca2",
    "type": "split",
    "children": [
      {
        "id": "4af724e31c2ead80",
        "type": "tabs",
        "children": [
          {
            "id": "964b2f6c57173d6f",
            "type": "leaf",
            "state": {
              "type": "markdown",
              "state": {
                "file": "React/FullStack Course/Part 9 TypeScript/Exercises/9d.md",
                "mode": "source",
                "source": false
              }
            }
          },
          {
            "id": "6957beaa3bb297a9",
            "type": "leaf",
            "state": {
              "type": "markdown",
              "state": {
                "file": "React/Ultimate React/Testing React/Exercises.md",
                "mode": "source",
                "source": false
              }
            }
          }
        ],
        "currentTab": 1
      }
    ],
    "direction": "vertical"
  },
  "left": {
    "id": "d2335838199974fc",
    "type": "split",
    "children": [
      {
        "id": "3ea403fbd3945804",
        "type": "tabs",
        "children": [
          {
            "id": "b3ffc8a5a142f4c5",
            "type": "leaf",
            "state": {
              "type": "file-explorer",
              "state": {
                "sortOrder": "alphabetical"
              }
            }
          },
          {
            "id": "c349099977dfd285",
            "type": "leaf",
            "state": {
              "type": "search",
              "state": {
                "query": "spread",
                "matchingCase": false,
                "explainSearch": false,
                "collapseAll": false,
                "extraContext": false,
                "sortOrder": "alphabetical"
              }
            }
          },
          {
            "id": "b53421fc8355ba6a",
            "type": "leaf",
            "state": {
              "type": "starred",
              "state": {}
            }
          },
          {
            "id": "16dd1923f0004169",
            "type": "leaf",
            "state": {
              "type": "bookmarks",
              "state": {}
            }
          }
        ]
      }
    ],
    "direction": "horizontal",
    "width": 300.5
  },
  "right": {
    "id": "54b7ae893977155b",
    "type": "split",
    "children": [
      {
        "id": "2641150572c48e06",
        "type": "tabs",
        "children": [
          {
            "id": "bcdf3ddfb2d9a488",
            "type": "leaf",
            "state": {
              "type": "backlink",
              "state": {
                "file": "React/Ultimate React/Testing React/Exercises.md",
                "collapseAll": false,
                "extraContext": false,
                "sortOrder": "alphabetical",
                "showSearch": false,
                "searchQuery": "",
                "backlinkCollapsed": false,
                "unlinkedCollapsed": true
              }
            }
          },
          {
            "id": "302a65b9f19cbc8e",
            "type": "leaf",
            "state": {
              "type": "outgoing-link",
              "state": {
                "file": "React/Ultimate React/Testing React/Exercises.md",
                "linksCollapsed": false,
                "unlinkedCollapsed": true
              }
            }
          },
          {
            "id": "3c1e30ecb7b33fe1",
            "type": "leaf",
            "state": {
              "type": "tag",
              "state": {
                "sortOrder": "frequency",
                "useHierarchy": true
              }
            }
          },
          {
            "id": "3c557ef07c20e6c0",
            "type": "leaf",
            "state": {
              "type": "outline",
              "state": {
                "file": "React/Ultimate React/Testing React/Exercises.md"
              }
            }
          },
          {
            "id": "0d4e927b0b513064",
            "type": "leaf",
            "state": {
              "type": "side-panel-control-view",
              "state": {}
            }
          }
        ],
        "currentTab": 4
      }
    ],
    "direction": "horizontal",
    "width": 300,
    "collapsed": true
  },
  "left-ribbon": {
    "hiddenItems": {
      "switcher:Open quick switcher": false,
      "graph:Open graph view": false,
      "canvas:Create new canvas": false,
      "daily-notes:Open today's daily note": false,
      "templates:Insert template": false,
      "command-palette:Open command palette": false,
      "obsidian-markdown-formatting-assistant-plugin:Open Markdown Formatting Assistant": false
    }
  },
  "active": "6957beaa3bb297a9",
  "lastOpenFiles": [
    "React/Ultimate React/Testing React/Resources.md",
    "React/Ultimate React/Testing React/General Tips.md",
    "React/Ultimate React/Testing React/Exercises.md",
    "Angular/Work Lessons/Testing Observables.md",
    "Interviews/Meli.md",
    "React/FullStack Course/Part 9 TypeScript/Exercises/9d.md",
    "React/FullStack Course/Part 9 TypeScript/Exercises/9c.md",
    "React/FullStack Course/Part 9 TypeScript/Exercises/9b.md",
    "React/FullStack Course/Part 9 TypeScript/9c Typing an Express app.md",
    "React/FullStack Course/Part 9 TypeScript/9d React with Types.md",
    "React/FullStack Course/Part 9 TypeScript/9e Grand Finale.md",
    "React/FullStack Course/Part 9 TypeScript/Exercises/9e.md",
    "Interviews/Applica Corp.md",
    "Interviews/Patterns/Problem solving.md",
    "Interviews/System Design/Interview Strategies/General Tips.md",
    "Interviews/Algorithms/Crystal Balls Problem.md",
    "Interviews/Algorithms/Recursion.md",
    "Interviews/FSL (Fullstack Labs)/Script.md",
    "React/Redux/Misc Tips.md",
    "Interviews/FSL (Fullstack Labs)/Coding Challenge.md",
    "Interviews/System Design/Sorting Algs.md",
    "Interviews/System Design/SLA.md",
    "React/Redux/RTK Query.md",
    "React/Redux/Terminology.md",
    "React/Redux/General Info.md",
    "React/Misc Resources/Misc.md",
    "VIM Config/Untitled",
    "Git Config",
    "DevOps Bootcamp",
    "React/FullStack Course/Part 9 TypeScript/Exercises",
    "React/FullStack Course/Part 9 TypeScript",
    "Tmux",
    "Interviews/FSL (Fullstack Labs)"
  ]
}